[
  {
    "CountryName": "China",
    "MPro": 41434820,
    "Methane": 169727400.47
  },
  {
    "CountryName": "United States",
    "MPro": 89015235,
    "Methane": 51494800.8225
  },
  {
    "CountryName": "Aruba",
    "MPro": 0,
    "Methane": 2200.968107
  },
  {
    "CountryName": "Andorra",
    "MPro": 0,
    "Methane": 0
  },
  {
    "CountryName": "Afghanistan",
    "MPro": 1740100,
    "Methane": 1362800.233
  },
  {
    "CountryName": "Angola",
    "MPro": 184000,
    "Methane": 1878800.424
  },
  {
    "CountryName": "Albania",
    "MPro": 1101010,
    "Methane": 261800.2937
  }
 ] 